pyprotect_package-1.3.dist-info/WHEEL
pyprotect_package-1.3.dist-info/RECORD
pyprotect_package-1.3.dist-info/top_level.txt
pyprotect_package-1.3.dist-info/LICENSE
pyprotect_package-1.3.dist-info/METADATA
pyprotect/HiddenPartial.pxi
pyprotect/protected.cpython-39-x86_64-linux-musl.so
pyprotect/__init__.py
pyprotect/global_c_functions.pxi
pyprotect/imports.pxi
pyprotect/Proxy.pxi
pyprotect/protected.pyx
pyprotect/python_visible.pxi
pyprotect/Wrapped_Frozen.pxi
pyprotect/global_cdefs.pxi
pyprotect/Private_FrozenPrivate.pxi
pyprotect/protected.c
pyprotect/Protected_FrozenProtected.pxi
pyprotect/PrivacyDict_FrozenPrivacyDict.pxi
pyprotect/ProtectionData.pxi
