Metadata-Version: 2.1
Name: pyprotect-package
Version: 1.3
Summary: Protect class attributes in any python object instance
Home-page: https://github.com/sundarnagarajan/pyprotect
Author: Sundar Nagarajan'
Author-email: sun.nagarajan@gmail.com
License: BSD
Project-URL: Source, https://github.com/sundarnagarajan/pyprotect
Project-URL: Tracker, https://github.com/sundarnagarajan/pyprotect/issues
Project-URL: Documentation, https://github.com/sundarnagarajan/pyprotect/blob/main/README.md
Keywords: private private_attributes frozen immutable freeze,frozen_object immutable_object freeze_object venv,virtualenv pypy pypy3
Platform: UNKNOWN
Classifier: Development Status :: 3 - Alpha
Classifier: Intended Audience :: Developers
Classifier: Topic :: Software Development :: Libraries
Classifier: Natural Language :: English
Classifier: Operating System :: POSIX :: Linux
Classifier: Programming Language :: Python :: 2.7
Classifier: Programming Language :: Python :: 3
Classifier: Programming Language :: Cython
Classifier: License :: OSI Approved :: BSD License
